BibleHubScrapper/BibleHubScrapper.py
BibleHubScrapper/__init__.py
BibleHubScrapper/config.py
BibleHubScrapper-1.3.4.data/scripts/biblehub
BibleHubScrapper-1.3.4.dist-info/LICENSE
BibleHubScrapper-1.3.4.dist-info/METADATA
BibleHubScrapper-1.3.4.dist-info/WHEEL
BibleHubScrapper-1.3.4.dist-info/top_level.txt
BibleHubScrapper-1.3.4.dist-info/RECORD
