Metadata-Version: 2.1
Name: BibleHubScrapper
Version: 1.3.4
Summary: A module to scrape biblehub.com, also cli app
Home-page: https://github.com/joshpetit/BibleHubScrapper
Author: Joshua Petitma
Author-email: joshuapetitma@yahoo.com
License: UNKNOWN
Platform: UNKNOWN
Classifier: Programming Language :: Python :: 3
Classifier: Programming Language :: Python :: 3.8
Classifier: License :: OSI Approved :: MIT License
Classifier: Operating System :: OS Independent
Requires-Python: >=3.6
